flox_github/__init__.py
flox_github/configure.py
flox_github/docker.py
flox_github/helper.py
flox_github/project.py
flox_github/remote.py
flox_github/workflow.py
flox_github-0.2.1.dist-info/entry_points.txt
flox_github-0.2.1.dist-info/LICENSE
flox_github-0.2.1.dist-info/WHEEL
flox_github-0.2.1.dist-info/METADATA
flox_github-0.2.1.dist-info/RECORD
